MANIFEST.in
README.txt
setup.cfg
setup.py
atreal/__init__.py
atreal/__init__.pyc
atreal.mailservices.egg-info/PKG-INFO
atreal.mailservices.egg-info/SOURCES.txt
atreal.mailservices.egg-info/dependency_links.txt
atreal.mailservices.egg-info/entry_points.txt
atreal.mailservices.egg-info/namespace_packages.txt
atreal.mailservices.egg-info/not-zip-safe
atreal.mailservices.egg-info/requires.txt
atreal.mailservices.egg-info/top_level.txt
atreal/mailservices/__init__.py
atreal/mailservices/__init__.pyc
atreal/mailservices/configure.zcml
atreal/mailservices/interfaces.py
atreal/mailservices/interfaces.pyc
atreal/mailservices/rebuild_i18n.sh
atreal/mailservices/browser/__init__.py
atreal/mailservices/browser/__init__.pyc
atreal/mailservices/browser/configure.zcml
atreal/mailservices/browser/controlpanel.py
atreal/mailservices/browser/controlpanel.pyc
atreal/mailservices/browser/forms.py
atreal/mailservices/browser/forms.pyc
atreal/mailservices/browser/macro_group_wrapper.pt
atreal/mailservices/browser/macro_user_wrapper.pt
atreal/mailservices/browser/mailservices.kss
atreal/mailservices/browser/mailservices.pt
atreal/mailservices/browser/mailservices_icon.png
atreal/mailservices/browser/overrides.py
atreal/mailservices/browser/overrides.pyc
atreal/mailservices/browser/views.py
atreal/mailservices/browser/views.pyc
atreal/mailservices/browser/widgets.py
atreal/mailservices/locales/atreal.mailservices.pot
atreal/mailservices/locales/en/LC_MESSAGES/atreal.mailservices.mo
atreal/mailservices/locales/en/LC_MESSAGES/atreal.mailservices.po
atreal/mailservices/locales/fr/LC_MESSAGES/atreal.mailservices.mo
atreal/mailservices/locales/fr/LC_MESSAGES/atreal.mailservices.po
atreal/mailservices/locales/nl/LC_MESSAGES/atreal.mailservices.mo
atreal/mailservices/locales/nl/LC_MESSAGES/atreal.mailservices.po
atreal/mailservices/profiles/default/actionicons.xml
atreal/mailservices/profiles/default/actions.xml
atreal/mailservices/profiles/default/browserlayer.xml
atreal/mailservices/profiles/default/controlpanel.xml
atreal/mailservices/profiles/default/kssregistry.xml
atreal/mailservices/profiles/default/metadata.xml
atreal/mailservices/profiles/default/rolemap.xml
docs/HISTORY.txt
docs/INSTALL.txt
docs/LICENSE.GPL
docs/LICENSE.txt