Metadata-Version: 1.0
Name: atreal.mailservices
Version: 1.1.0
Summary: Send mails from Plone to users and groups
Home-page: http://www.atreal.net/
Author: atReal
Author-email: contact@atreal.net
License: GPL
Platform: UNKNOWN
Classifier: Framework :: Plone
Classifier: Programming Language :: Python
Classifier: Topic :: Software Development :: Libraries :: Python Modules
